gpp_components/__init__.py
gpp_components/aes.py
gpp_components/constant.py
gpp_components/dbConfig.py
gpp_components/decorator.py
gpp_components/dellCalendar.py
gpp_components/fileImporter.py
gpp_components/handleData.py
gpp_components/lazyImport.py
gpp_components/response.py
gpp_components/runOracle.py
gpp_components/sendMail.py
gpp_components/year_quar_week.json
gpp_components-0.1.15.dist-info/LICENSE
gpp_components-0.1.15.dist-info/METADATA
gpp_components-0.1.15.dist-info/WHEEL
gpp_components-0.1.15.dist-info/top_level.txt
gpp_components-0.1.15.dist-info/RECORD
