Metadata-Version: 2.1
Name: gpp_components
Version: 0.1.15
Summary: for internal use
Author: L
License: MIT Licence
License-File: LICENSE
Requires-Dist: pycryptodome
Requires-Dist: django
Requires-Dist: oracledb
Requires-Dist: pandas
Requires-Dist: jsonpath
Requires-Dist: rich
Requires-Dist: SQLAlchemy
